sc_req-1.4.0.dist-info/licenses/LICENSE
sphinxcontrib/requirement/__init__.py
sphinxcontrib/requirement/__main__.py
sphinxcontrib/requirement/req.css
sphinxcontrib/requirement/req.html.jinja2
sphinxcontrib/requirement/req.latex.jinja2
sphinxcontrib/requirement/req.preamble
sphinxcontrib/requirement/req.py
sphinxcontrib/requirement/req.rst.jinja2
sphinxcontrib/requirement/reqlist.rst.jinja2
sc_req-1.4.0.dist-info/METADATA
sc_req-1.4.0.dist-info/WHEEL
sc_req-1.4.0.dist-info/top_level.txt
sc_req-1.4.0.dist-info/RECORD
