Metadata-Version: 2.4
Name: sc-req
Version: 1.4.0
Summary: Sphinx extension for managing requirements
Home-page: https://github.com/olivier-heurtier/sphinxcontrib-requirement/tree/main
Author: Olivier Heurtier
Author-email: olivier.heurtier@free.fr
License: Apache-2.0
Classifier: Topic :: Documentation
Classifier: Topic :: Documentation :: Sphinx
Classifier: Environment :: Console
Classifier: Intended Audience :: Developers
Classifier: Operating System :: OS Independent
Classifier: Programming Language :: Python
Classifier: Programming Language :: Python :: 3
Classifier: Programming Language :: Python :: 3 :: Only
Classifier: Programming Language :: Python :: 3.9
Classifier: Programming Language :: Python :: 3.10
Classifier: Programming Language :: Python :: 3.11
Classifier: Programming Language :: Python :: 3.12
Classifier: Programming Language :: Python :: Implementation :: CPython
Classifier: Framework :: Sphinx
Classifier: Framework :: Sphinx :: Extension
Requires-Python: >=3.9
License-File: LICENSE
Requires-Dist: sphinx>=7.4
Requires-Dist: Jinja2
Dynamic: license-file
